README.rst
setup.py
authconnector/__init__.py
authconnector/apps.py
authconnector/authentication.py
authconnector/exceptions.py
authconnector.egg-info/PKG-INFO
authconnector.egg-info/SOURCES.txt
authconnector.egg-info/dependency_links.txt
authconnector.egg-info/requires.txt
authconnector.egg-info/top_level.txt