Metadata-Version: 1.1
Name: authconnector
Version: 1.0.1
Summary: This project contains the basic authentication against the remote JWT service.
Home-page: https://github.com/Tibiritabara/django-auth-connector.git
Author: Ricardo Santos
Author-email: ricardo.santos.diaz@gmail.com
License: GNU Public License
Platform: UNKNOWN
Classifier: Framework :: Django
Classifier: Intended Audience :: Developers
Classifier: License :: OSI Approved :: MIT License
Classifier: Operating System :: OS Independent
Classifier: Programming Language :: Python :: 3.6
